{
  "version": 1,
  "updated_at_london": "2026-05-20T08:01:41.625488+01:00",
  "entries": {
    "https://feeds.bbci.co.uk/news/england/manchester/rss.xml": {
      "fetched_at": "2026-05-20T08:00:52.401357+01:00",
      "status": "200"
    },
    "https://altrincham.todaynews.co.uk/": {
      "etag": "W/\"25ee8-Pqsri1Kg++HItlC2ZTTqWYmPxew\"",
      "fetched_at": "2026-05-20T08:00:52.565687+01:00",
      "status": "200"
    },
    "https://manchestermill.co.uk/rss/": {
      "etag": "W/\"1f59a-1SZ/p1rieVdehmEDF49x/bh7FXE\"",
      "fetched_at": "2026-05-20T08:00:52.579585+01:00",
      "status": "200"
    },
    "https://www.manchestereveningnews.co.uk/": {
      "fetched_at": "2026-05-20T08:00:52.805857+01:00",
      "status": "200"
    },
    "https://themanc.com/category/news/": {
      "last_modified": "Wed, 20 May 2026 06:47:50 GMT",
      "fetched_at": "2026-05-20T08:00:52.812037+01:00",
      "status": "200"
    },
    "https://ilovemanchester.com/feed": {
      "etag": "\"693204102810b6cd49b4016019b6c9d6\"",
      "last_modified": "Tue, 19 May 2026 16:02:31 GMT",
      "fetched_at": "2026-05-20T08:00:52.835120+01:00",
      "status": "200"
    },
    "https://secretmanchester.com/feed": {
      "fetched_at": "2026-05-20T08:00:54.057980+01:00",
      "status": "200"
    },
    "https://www.bbc.com/news/england/manchester": {
      "fetched_at": "2026-05-20T08:00:54.479551+01:00",
      "status": "200"
    },
    "https://www.nationalrail.co.uk/status-and-disruptions/": {
      "fetched_at": "2026-05-20T08:00:54.967629+01:00",
      "status": "200"
    },
    "https://tfgm.com/travel-updates/travel-alerts": {
      "fetched_at": "2026-05-20T08:00:55.028554+01:00",
      "status": "200"
    },
    "https://www.greatermanchester-ca.gov.uk/": {
      "fetched_at": "2026-05-20T08:00:55.930112+01:00",
      "status": "200"
    },
    "https://manchester2-search.funnelback.squiz.cloud/s/search.json?collection=manchester~sp-search&profile=news-archive_preview&query=&sort=dmetatimestamp&num_ranks=20&gscope1=news": {
      "last_modified": "Wed, 20 May 2026 07:00:56 GMT",
      "fetched_at": "2026-05-20T08:00:56.864272+01:00",
      "status": "200"
    },
    "https://www.stockport.gov.uk/newsroom?page=1&pageSize=60&type=rss&view=Standard": {
      "fetched_at": "2026-05-20T08:00:58.885642+01:00",
      "status": "200"
    },
    "https://www.oldham.gov.uk/rss/news": {
      "fetched_at": "2026-05-20T08:00:59.186492+01:00",
      "status": "200"
    },
    "https://www.rochdale.gov.uk/rss/news": {
      "fetched_at": "2026-05-20T08:00:59.468630+01:00",
      "status": "200"
    },
    "https://www.gmmh.nhs.uk/news/": {
      "fetched_at": "2026-05-20T08:01:01.433512+01:00",
      "status": "200"
    },
    "https://www.bolton.gov.uk/rss/news": {
      "fetched_at": "2026-05-20T08:01:02.974521+01:00",
      "status": "200"
    },
    "https://www.mynewsdesk.com/uk/rss/current_news/49585": {
      "etag": "W/\"ec78ebeb28963417981bd39781a8d361\"",
      "fetched_at": "2026-05-20T08:01:02.990639+01:00",
      "status": "200"
    },
    "https://www.wigan.gov.uk/News/News.aspx": {
      "fetched_at": "2026-05-20T08:01:05.932296+01:00",
      "status": "200"
    },
    "https://www.whitworth.manchester.ac.uk/whats-on/events/": {
      "fetched_at": "2026-05-20T08:01:08.750969+01:00",
      "status": "200"
    },
    "https://homemcr.org/whats-on/": {
      "fetched_at": "2026-05-20T08:01:08.979585+01:00",
      "status": "200"
    },
    "https://factoryinternational.org/whats-on/": {
      "fetched_at": "2026-05-20T08:01:09.133394+01:00",
      "status": "200"
    },
    "https://www.atgtickets.com/venues/palace-theatre-manchester/whats-on/": {
      "fetched_at": "2026-05-20T08:01:12.019044+01:00",
      "status": "200"
    },
    "https://thelowry.com/whats-on": {
      "fetched_at": "2026-05-20T08:01:12.207280+01:00",
      "status": "200"
    },
    "https://contactmcr.com/whats-on/": {
      "fetched_at": "2026-05-20T08:01:14.826287+01:00",
      "status": "200"
    },
    "https://phm.org.uk/whats-on/": {
      "fetched_at": "2026-05-20T08:01:15.406036+01:00",
      "status": "200"
    },
    "https://www.library.manchester.ac.uk/rylands/visit/events/": {
      "fetched_at": "2026-05-20T08:01:16.535273+01:00",
      "status": "200"
    },
    "https://www.visitmanchester.com/whats-on": {
      "fetched_at": "2026-05-20T08:01:18.138732+01:00",
      "status": "200"
    },
    "https://www.manchestersfinest.com/events/": {
      "fetched_at": "2026-05-20T08:01:18.617335+01:00",
      "status": "200"
    },
    "https://app.ticketmaster.com/discovery/v2/events.json?city=Manchester&countryCode=GB&classificationName=music&size=50&sort=onSaleStartDate,asc&onsaleStartDateTime=2026-05-19T07:01:18Z&onsaleEndDateTime=2026-06-03T07:01:18Z&apikey=7AmOL3vKAGGDIGbGgcGnL1H99nO7fX3X": {
      "fetched_at": "2026-05-20T08:01:19.013864+01:00",
      "status": "200"
    },
    "https://app.ticketmaster.com/discovery/v2/events.json?city=Liverpool&countryCode=GB&classificationName=music&size=50&sort=onSaleStartDate,asc&onsaleStartDateTime=2026-05-19T07:01:19Z&onsaleEndDateTime=2026-06-03T07:01:19Z&apikey=7AmOL3vKAGGDIGbGgcGnL1H99nO7fX3X": {
      "fetched_at": "2026-05-20T08:01:19.816581+01:00",
      "status": "200"
    },
    "https://app.ticketmaster.com/discovery/v2/events.json?city=Manchester&countryCode=GB&classificationName=music&size=50&sort=date,asc&startDateTime=2026-05-20T07:01:19Z&endDateTime=2026-06-19T07:01:19Z&apikey=7AmOL3vKAGGDIGbGgcGnL1H99nO7fX3X": {
      "fetched_at": "2026-05-20T08:01:20.011148+01:00",
      "status": "200"
    },
    "https://app.ticketmaster.com/discovery/v2/events.json?city=Liverpool&countryCode=GB&classificationName=music&size=50&sort=date,asc&startDateTime=2026-05-20T07:01:19Z&endDateTime=2026-06-19T07:01:19Z&apikey=7AmOL3vKAGGDIGbGgcGnL1H99nO7fX3X": {
      "fetched_at": "2026-05-20T08:01:20.371736+01:00",
      "status": "200"
    },
    "https://app.ticketmaster.com/discovery/v2/events.json?city=London&countryCode=GB&classificationName=music&size=100&sort=onSaleStartDate,asc&onsaleStartDateTime=2026-05-19T07:01:20Z&onsaleEndDateTime=2026-06-03T07:01:20Z&apikey=7AmOL3vKAGGDIGbGgcGnL1H99nO7fX3X": {
      "fetched_at": "2026-05-20T08:01:20.814270+01:00",
      "status": "200"
    },
    "https://app.ticketmaster.com/discovery/v2/events.json?city=London&countryCode=GB&classificationName=music&size=100&sort=date,asc&startDateTime=2026-05-20T07:01:20Z&endDateTime=2026-06-19T07:01:20Z&apikey=7AmOL3vKAGGDIGbGgcGnL1H99nO7fX3X": {
      "fetched_at": "2026-05-20T08:01:20.951615+01:00",
      "status": "200"
    },
    "https://www.cooplive.com/events": {
      "fetched_at": "2026-05-20T08:01:21.120389+01:00",
      "status": "200"
    },
    "https://alberthallmanchester.com/event-sitemap.xml": {
      "fetched_at": "2026-05-20T08:01:21.581541+01:00",
      "status": "200"
    },
    "https://bandonthewall.org/feed/": {
      "etag": "\"b676bb1fc6ecfc89afab1eed989f0eef\"",
      "fetched_at": "2026-05-20T08:01:21.598232+01:00",
      "status": "200"
    },
    "https://www.bridgewater-hall.co.uk/whats-on/": {
      "fetched_at": "2026-05-20T08:01:21.938709+01:00",
      "status": "200"
    },
    "https://ukstandupclub.co.uk/": {
      "etag": "780376ab9cc3dd6d3f23838201c0631c",
      "fetched_at": "2026-05-20T08:01:22.225407+01:00",
      "status": "200"
    },
    "https://www.rncm.ac.uk/whats-on/": {
      "last_modified": "Wed, 20 May 2026 07:01:22 GMT",
      "fetched_at": "2026-05-20T08:01:22.260694+01:00",
      "status": "200"
    },
    "https://eventfirst.co.uk/": {
      "fetched_at": "2026-05-20T08:01:22.810203+01:00",
      "status": "200"
    },
    "https://www.eventbrite.com/o/uk-stand-up-club-35496769133": {
      "etag": "W/\"i36fph7sx83ewj\"",
      "fetched_at": "2026-05-20T08:01:23.136425+01:00",
      "status": "200"
    },
    "https://kontramarka.uk/": {
      "fetched_at": "2026-05-20T08:01:23.558553+01:00",
      "status": "200"
    },
    "https://www.manchestersfinest.com/category/eating-and-drinking/": {
      "fetched_at": "2026-05-20T08:01:24.005983+01:00",
      "status": "200"
    },
    "https://themanc.com/eats/": {
      "last_modified": "Wed, 20 May 2026 06:39:01 GMT",
      "fetched_at": "2026-05-20T08:01:24.743882+01:00",
      "status": "200"
    },
    "https://aboutmanchester.co.uk/category/food-drink/openings/": {
      "last_modified": "Tue, 19 May 2026 13:06:20 GMT",
      "fetched_at": "2026-05-20T08:01:24.799058+01:00",
      "status": "200"
    },
    "https://pedddle.com/": {
      "fetched_at": "2026-05-20T08:01:26.057032+01:00",
      "status": "200"
    },
    "https://pedddle.com/organiser/makers-market/": {
      "fetched_at": "2026-05-20T08:01:26.319695+01:00",
      "status": "200"
    },
    "https://www.visitsalford.info/events/": {
      "fetched_at": "2026-05-20T08:01:26.810212+01:00",
      "status": "200"
    },
    "https://ma.to/venue/remarket_mcr": {
      "fetched_at": "2026-05-20T08:01:27.151825+01:00",
      "status": "200"
    },
    "https://www.sklowdown.co.uk/whats-on-stockport/": {
      "etag": "W/\"a37c811878f67ef6a1d4de1816645961\"",
      "fetched_at": "2026-05-20T08:01:27.345361+01:00",
      "status": "200"
    },
    "https://www.manchesterdigital.com/": {
      "fetched_at": "2026-05-20T08:01:27.543367+01:00",
      "status": "200"
    },
    "https://www.prolificnorth.co.uk/feed/": {
      "last_modified": "Wed, 20 May 2026 01:17:31 GMT",
      "fetched_at": "2026-05-20T08:01:28.115548+01:00",
      "status": "200"
    },
    "https://businesscloud.co.uk/feed/": {
      "etag": "\"7256ab0114cdab15b0e65978e75ef457\"",
      "last_modified": "Wed, 20 May 2026 06:34:55 GMT",
      "fetched_at": "2026-05-20T08:01:28.805058+01:00",
      "status": "200"
    },
    "https://bdaily.co.uk/region/north-west": {
      "fetched_at": "2026-05-20T08:01:28.835952+01:00",
      "status": "200"
    },
    "https://www.investinmanchester.com/news/": {
      "last_modified": "Wed, 20 May 2026 01:24:10 GMT",
      "fetched_at": "2026-05-20T08:01:29.105131+01:00",
      "status": "200"
    },
    "https://www.salford.ac.uk/news/rss": {
      "etag": "\"1779224923\"",
      "last_modified": "Tue, 19 May 2026 21:08:43 GMT",
      "fetched_at": "2026-05-20T08:01:29.283386+01:00",
      "status": "200"
    },
    "https://www.manchester.ac.uk/about/news/feed/": {
      "last_modified": "Wed, 20 May 2026 07:00:45 GMT",
      "fetched_at": "2026-05-20T08:01:29.384883+01:00",
      "status": "200"
    },
    "https://manchesterwire.co.uk/": {
      "fetched_at": "2026-05-20T08:01:30.822879+01:00",
      "status": "200"
    },
    "https://www.creativetourist.com/whats-on/": {
      "fetched_at": "2026-05-20T08:01:31.170143+01:00",
      "status": "200"
    },
    "https://www.designmynight.com/manchester/whats-on/things-to-do-this-weekend-in-manchester": {
      "fetched_at": "2026-05-20T08:01:31.486315+01:00",
      "status": "200"
    },
    "https://fscmcr.co.uk/": {
      "etag": "W/\"d6f2c1df938440831c621fd45442cc37--gzip\"",
      "fetched_at": "2026-05-20T08:01:31.768754+01:00",
      "status": "200"
    },
    "https://www.skiddle.com/whats-on/Manchester/": {
      "etag": "\"as26dbdxeapbko\"",
      "fetched_at": "2026-05-20T08:01:32.681363+01:00",
      "status": "200"
    },
    "https://www.manchestersfinest.com/events/peoples-history-museum-makers-market/": {
      "fetched_at": "2026-05-20T08:01:33.072740+01:00",
      "status": "200"
    },
    "https://tickets.foodfestivaltickets.com/events/foodfestival/1883190": {
      "last_modified": "Wed, 20 May 2026 07:01:33 GMT",
      "fetched_at": "2026-05-20T08:01:33.512077+01:00",
      "status": "200"
    },
    "https://www.firststreetmanchester.com/news/makers-market-double-header-this-may/": {
      "fetched_at": "2026-05-20T08:01:33.522767+01:00",
      "status": "200"
    },
    "https://www.spinningfields.co.uk/event/makers-market/": {
      "etag": "\"516-1779144417;;;\"",
      "fetched_at": "2026-05-20T08:01:34.122317+01:00",
      "status": "200"
    },
    "https://www.themakersmarket.co.uk/market/levenshulme-2/": {
      "fetched_at": "2026-05-20T08:01:34.389330+01:00",
      "status": "200"
    },
    "https://pedddle.com/market/northern-quarter-makers-market/": {
      "fetched_at": "2026-05-20T08:01:34.440566+01:00",
      "status": "200"
    },
    "https://pedddle.com/market/stockport-makers-market/": {
      "fetched_at": "2026-05-20T08:01:34.619369+01:00",
      "status": "200"
    },
    "https://pedddle.com/market/urmston-artisan-market/": {
      "fetched_at": "2026-05-20T08:01:34.739803+01:00",
      "status": "200"
    },
    "https://visitaltrincham.com/business-directory/altrincham-market/": {
      "fetched_at": "2026-05-20T08:01:35.383596+01:00",
      "status": "200"
    },
    "https://www.manchester-rocks.co.uk/things-to-do/barton-aerodrome-car-boot-sale": {
      "etag": "\"d3jkmtdzhs4yu1\"",
      "fetched_at": "2026-05-20T08:01:35.451224+01:00",
      "status": "200"
    },
    "https://www.thegreatnorthern.com/event/makers-market-in-great-northern-square/": {
      "fetched_at": "2026-05-20T08:01:35.463937+01:00",
      "status": "200"
    },
    "https://www.rochdale.gov.uk/news/article/592/bowlee-is-back---car-boot-sale-and-market-returns-for-new-season": {
      "fetched_at": "2026-05-20T08:01:35.730445+01:00",
      "status": "200"
    },
    "https://www.manchester-rocks.co.uk/things-to-do/burnage-rfc-car-boot-sale": {
      "etag": "\"cksb3sreh545yv\"",
      "fetched_at": "2026-05-20T08:01:35.949756+01:00",
      "status": "200"
    },
    "https://www.manchester-rocks.co.uk/things-to-do/the-big-stockport-car-boot-romiley": {
      "etag": "\"4o4l101vdz71oq\"",
      "fetched_at": "2026-05-20T08:01:36.097236+01:00",
      "status": "200"
    },
    "https://www.manchester.gov.uk/newsmithfieldmarket": {
      "fetched_at": "2026-05-20T08:01:36.270222+01:00",
      "status": "200"
    },
    "https://carbootdirectory.co.uk/listings/bolton-car-boot/": {
      "fetched_at": "2026-05-20T08:01:36.330269+01:00",
      "status": "200"
    },
    "https://themanc.com/whats-on-manchester/the-best-things-to-do-in-greater-manchester-this-week-11-17-may-2026/": {
      "last_modified": "Wed, 20 May 2026 07:00:51 GMT",
      "fetched_at": "2026-05-20T08:01:36.622650+01:00",
      "status": "200"
    },
    "https://warringtoncarboot.com/": {
      "etag": "\"152173-6a0d47f1-817f4d8583457bea;;;\"",
      "last_modified": "Wed, 20 May 2026 05:34:41 GMT",
      "fetched_at": "2026-05-20T08:01:36.646774+01:00",
      "status": "200"
    },
    "https://chorlton.coop/series/chorlton-makers-market/": {
      "fetched_at": "2026-05-20T08:01:36.739289+01:00",
      "status": "200"
    },
    "https://www.manutd.com/en/news": {
      "last_modified": "Wed, 20 May 2026 04:23:54 GMT",
      "fetched_at": "2026-05-20T08:01:36.889931+01:00",
      "status": "200"
    },
    "https://www.timeout.com/manchester/things-to-do": {
      "fetched_at": "2026-05-20T08:01:37.114691+01:00",
      "status": "200"
    },
    "https://www.mancity.com/news": {
      "fetched_at": "2026-05-20T08:01:37.332687+01:00",
      "status": "200"
    },
    "https://www.stockport.gov.uk/events/rss": {
      "fetched_at": "2026-05-20T08:01:37.580663+01:00",
      "status": "200"
    }
  }
}